{"track":[{"idTrack":"32730355","idAlbum":"2110242","idArtist":"111280","idLyric":"176229","idIMVDB":null,"strTrack":"Skies the Limit","strAlbum":"Behind the Mask","strArtist":"Fleetwood Mac","strArtistAlternate":null,"intCD":null,"intDuration":"225306","strGenre":"Rock","strMood":null,"strStyle":null,"strTheme":null,"strDescriptionEN":null,"strTrackThumb":null,"strTrack3DCase":null,"strTrackLyrics":null,"strMusicVid":null,"strMusicVidDirector":null,"strMusicVidCompany":null,"strMusicVidScreen1":null,"strMusicVidScreen2":null,"strMusicVidScreen3":null,"intMusicVidViews":null,"intMusicVidLikes":null,"intMusicVidDislikes":null,"intMusicVidFavorites":null,"intMusicVidComments":null,"intTrackNumber":"1","intLoved":"0","intScore":null,"intScoreVotes":null,"intTotalListeners":null,"intTotalPlays":null,"strMusicBrainzID":"b3c18a17-e288-45ca-8ece-f72e41f856d1","strMusicBrainzAlbumID":"0088f94b-d9f5-37a0-a7ce-499319c6e8ee","strMusicBrainzArtistID":"bd13909f-1c29-4c27-a874-d4aaf27c5b1a","strLocked":"unlocked"},{"idTrack":"32730356","idAlbum":"2110242","idArtist":"111280","idLyric":"0","idIMVDB":null,"strTrack":"Love Is Dangerous","strAlbum":"Behind the Mask","strArtist":"Fleetwood Mac","strArtistAlternate":null,"intCD":null,"intDuration":"198200","strGenre":"Rock","strMood":null,"strStyle":null,"strTheme":null,"strDescriptionEN":null,"strTrackThumb":null,"strTrack3DCase":null,"strTrackLyrics":null,"strMusicVid":null,"strMusicVidDirector":null,"strMusicVidCompany":null,"strMusicVidScreen1":null,"strMusicVidScreen2":null,"strMusicVidScreen3":null,"intMusicVidViews":null,"intMusicVidLikes":null,"intMusicVidDislikes":null,"intMusicVidFavorites":null,"intMusicVidComments":null,"intTrackNumber":"2","intLoved":"0","intScore":null,"intScoreVotes":null,"intTotalListeners":null,"intTotalPlays":null,"strMusicBrainzID":"c9112169-870c-4ec3-af63-b5c09a44a9e8","strMusicBrainzAlbumID":"0088f94b-d9f5-37a0-a7ce-499319c6e8ee","strMusicBrainzArtistID":"bd13909f-1c29-4c27-a874-d4aaf27c5b1a","strLocked":"unlocked"},{"idTrack":"32730357","idAlbum":"2110242","idArtist":"111280","idLyric":"176227","idIMVDB":null,"strTrack":"In the Back of My Mind","strAlbum":"Behind the Mask","strArtist":"Fleetwood Mac","strArtistAlternate":null,"intCD":null,"intDuration":"422693","strGenre":"Rock","strMood":null,"strStyle":null,"strTheme":null,"strDescriptionEN":null,"strTrackThumb":null,"strTrack3DCase":null,"strTrackLyrics":null,"strMusicVid":null,"strMusicVidDirector":null,"strMusicVidCompany":null,"strMusicVidScreen1":null,"strMusicVidScreen2":null,"strMusicVidScreen3":null,"intMusicVidViews":null,"intMusicVidLikes":null,"intMusicVidDislikes":null,"intMusicVidFavorites":null,"intMusicVidComments":null,"intTrackNumber":"3","intLoved":"0","intScore":null,"intScoreVotes":null,"intTotalListeners":null,"intTotalPlays":null,"strMusicBrainzID":"f29c7d56-3946-4c2a-a869-08050a5b9a91","strMusicBrainzAlbumID":"0088f94b-d9f5-37a0-a7ce-499319c6e8ee","strMusicBrainzArtistID":"bd13909f-1c29-4c27-a874-d4aaf27c5b1a","strLocked":"unlocked"},{"idTrack":"32730358","idAlbum":"2110242","idArtist":"111280","idLyric":"176224","idIMVDB":null,"strTrack":"Do You Know","strAlbum":"Behind the Mask","strArtist":"Fleetwood Mac","strArtistAlternate":null,"intCD":null,"intDuration":"259306","strGenre":"Rock","strMood":null,"strStyle":null,"strTheme":null,"strDescriptionEN":null,"strTrackThumb":null,"strTrack3DCase":null,"strTrackLyrics":null,"strMusicVid":null,"strMusicVidDirector":null,"strMusicVidCompany":null,"strMusicVidScreen1":null,"strMusicVidScreen2":null,"strMusicVidScreen3":null,"intMusicVidViews":null,"intMusicVidLikes":null,"intMusicVidDislikes":null,"intMusicVidFavorites":null,"intMusicVidComments":null,"intTrackNumber":"4","intLoved":"0","intScore":null,"intScoreVotes":null,"intTotalListeners":null,"intTotalPlays":null,"strMusicBrainzID":"a68206a2-2049-4f39-a1fa-4eeaebb54bae","strMusicBrainzAlbumID":"0088f94b-d9f5-37a0-a7ce-499319c6e8ee","strMusicBrainzArtistID":"bd13909f-1c29-4c27-a874-d4aaf27c5b1a","strLocked":"unlocked"},{"idTrack":"32730359","idAlbum":"2110242","idArtist":"111280","idLyric":"176228","idIMVDB":null,"strTrack":"Save Me","strAlbum":"Behind the Mask","strArtist":"Fleetwood Mac","strArtistAlternate":null,"intCD":null,"intDuration":"255093","strGenre":"Rock","strMood":null,"strStyle":null,"strTheme":null,"strDescriptionEN":null,"strTrackThumb":null,"strTrack3DCase":null,"strTrackLyrics":null,"strMusicVid":null,"strMusicVidDirector":null,"strMusicVidCompany":null,"strMusicVidScreen1":null,"strMusicVidScreen2":null,"strMusicVidScreen3":null,"intMusicVidViews":null,"intMusicVidLikes":null,"intMusicVidDislikes":null,"intMusicVidFavorites":null,"intMusicVidComments":null,"intTrackNumber":"5","intLoved":"0","intScore":null,"intScoreVotes":null,"intTotalListeners":null,"intTotalPlays":null,"strMusicBrainzID":"78f473aa-c19f-42bd-913b-77faa37200d3","strMusicBrainzAlbumID":"0088f94b-d9f5-37a0-a7ce-499319c6e8ee","strMusicBrainzArtistID":"bd13909f-1c29-4c27-a874-d4aaf27c5b1a","strLocked":"unlocked"},{"idTrack":"32730360","idAlbum":"2110242","idArtist":"111280","idLyric":"176222","idIMVDB":null,"strTrack":"Affairs of the Heart","strAlbum":"Behind the Mask","strArtist":"Fleetwood Mac","strArtistAlternate":null,"intCD":null,"intDuration":"262106","strGenre":"Rock","strMood":null,"strStyle":null,"strTheme":null,"strDescriptionEN":null,"strTrackThumb":null,"strTrack3DCase":null,"strTrackLyrics":null,"strMusicVid":null,"strMusicVidDirector":null,"strMusicVidCompany":null,"strMusicVidScreen1":null,"strMusicVidScreen2":null,"strMusicVidScreen3":null,"intMusicVidViews":null,"intMusicVidLikes":null,"intMusicVidDislikes":null,"intMusicVidFavorites":null,"intMusicVidComments":null,"intTrackNumber":"6","intLoved":"0","intScore":null,"intScoreVotes":null,"intTotalListeners":null,"intTotalPlays":null,"strMusicBrainzID":"1b483fa2-c6cf-4c03-adf5-233c8ae8a595","strMusicBrainzAlbumID":"0088f94b-d9f5-37a0-a7ce-499319c6e8ee","strMusicBrainzArtistID":"bd13909f-1c29-4c27-a874-d4aaf27c5b1a","strLocked":"unlocked"},{"idTrack":"32730361","idAlbum":"2110242","idArtist":"111280","idLyric":"176233","idIMVDB":null,"strTrack":"When the Sun Goes Down","strAlbum":"Behind the Mask","strArtist":"Fleetwood Mac","strArtistAlternate":null,"intCD":null,"intDuration":"198560","strGenre":"Rock","strMood":null,"strStyle":null,"strTheme":null,"strDescriptionEN":null,"strTrackThumb":null,"strTrack3DCase":null,"strTrackLyrics":null,"strMusicVid":null,"strMusicVidDirector":null,"strMusicVidCompany":null,"strMusicVidScreen1":null,"strMusicVidScreen2":null,"strMusicVidScreen3":null,"intMusicVidViews":null,"intMusicVidLikes":null,"intMusicVidDislikes":null,"intMusicVidFavorites":null,"intMusicVidComments":null,"intTrackNumber":"7","intLoved":"0","intScore":null,"intScoreVotes":null,"intTotalListeners":null,"intTotalPlays":null,"strMusicBrainzID":"2c1abf5d-cc88-4129-8978-182fdbf0cc65","strMusicBrainzAlbumID":"0088f94b-d9f5-37a0-a7ce-499319c6e8ee","strMusicBrainzArtistID":"bd13909f-1c29-4c27-a874-d4aaf27c5b1a","strLocked":"unlocked"},{"idTrack":"32730362","idAlbum":"2110242","idArtist":"111280","idLyric":"176223","idIMVDB":null,"strTrack":"Behind the Mask","strAlbum":"Behind the Mask","strArtist":"Fleetwood Mac","strArtistAlternate":null,"intCD":null,"intDuration":"258200","strGenre":"Rock","strMood":null,"strStyle":null,"strTheme":null,"strDescriptionEN":null,"strTrackThumb":null,"strTrack3DCase":null,"strTrackLyrics":null,"strMusicVid":null,"strMusicVidDirector":null,"strMusicVidCompany":null,"strMusicVidScreen1":null,"strMusicVidScreen2":null,"strMusicVidScreen3":null,"intMusicVidViews":null,"intMusicVidLikes":null,"intMusicVidDislikes":null,"intMusicVidFavorites":null,"intMusicVidComments":null,"intTrackNumber":"8","intLoved":"0","intScore":null,"intScoreVotes":null,"intTotalListeners":null,"intTotalPlays":null,"strMusicBrainzID":"7186fa73-5e06-4fe6-b42f-a1986d47fa02","strMusicBrainzAlbumID":"0088f94b-d9f5-37a0-a7ce-499319c6e8ee","strMusicBrainzArtistID":"bd13909f-1c29-4c27-a874-d4aaf27c5b1a","strLocked":"unlocked"},{"idTrack":"32730363","idAlbum":"2110242","idArtist":"111280","idLyric":"176230","idIMVDB":null,"strTrack":"Stand on the Rock","strAlbum":"Behind the Mask","strArtist":"Fleetwood Mac","strArtistAlternate":null,"intCD":null,"intDuration":"239506","strGenre":"Rock","strMood":null,"strStyle":null,"strTheme":null,"strDescriptionEN":null,"strTrackThumb":null,"strTrack3DCase":null,"strTrackLyrics":null,"strMusicVid":null,"strMusicVidDirector":null,"strMusicVidCompany":null,"strMusicVidScreen1":null,"strMusicVidScreen2":null,"strMusicVidScreen3":null,"intMusicVidViews":null,"intMusicVidLikes":null,"intMusicVidDislikes":null,"intMusicVidFavorites":null,"intMusicVidComments":null,"intTrackNumber":"9","intLoved":"0","intScore":null,"intScoreVotes":null,"intTotalListeners":null,"intTotalPlays":null,"strMusicBrainzID":"f1b5261d-240d-4f6f-919e-0c303f288d56","strMusicBrainzAlbumID":"0088f94b-d9f5-37a0-a7ce-499319c6e8ee","strMusicBrainzArtistID":"bd13909f-1c29-4c27-a874-d4aaf27c5b1a","strLocked":"unlocked"},{"idTrack":"32730364","idAlbum":"2110242","idArtist":"111280","idLyric":"176226","idIMVDB":null,"strTrack":"Hard Feelings","strAlbum":"Behind the Mask","strArtist":"Fleetwood Mac","strArtistAlternate":null,"intCD":null,"intDuration":"294533","strGenre":"Rock","strMood":null,"strStyle":null,"strTheme":null,"strDescriptionEN":null,"strTrackThumb":null,"strTrack3DCase":null,"strTrackLyrics":null,"strMusicVid":null,"strMusicVidDirector":null,"strMusicVidCompany":null,"strMusicVidScreen1":null,"strMusicVidScreen2":null,"strMusicVidScreen3":null,"intMusicVidViews":null,"intMusicVidLikes":null,"intMusicVidDislikes":null,"intMusicVidFavorites":null,"intMusicVidComments":null,"intTrackNumber":"10","intLoved":"0","intScore":null,"intScoreVotes":null,"intTotalListeners":null,"intTotalPlays":null,"strMusicBrainzID":"24141221-c322-4227-a683-156e528a322c","strMusicBrainzAlbumID":"0088f94b-d9f5-37a0-a7ce-499319c6e8ee","strMusicBrainzArtistID":"bd13909f-1c29-4c27-a874-d4aaf27c5b1a","strLocked":"unlocked"},{"idTrack":"32730365","idAlbum":"2110242","idArtist":"111280","idLyric":"176225","idIMVDB":null,"strTrack":"Freedom","strAlbum":"Behind the Mask","strArtist":"Fleetwood Mac","strArtistAlternate":null,"intCD":null,"intDuration":"252493","strGenre":"Rock","strMood":null,"strStyle":null,"strTheme":null,"strDescriptionEN":null,"strTrackThumb":null,"strTrack3DCase":null,"strTrackLyrics":null,"strMusicVid":null,"strMusicVidDirector":null,"strMusicVidCompany":null,"strMusicVidScreen1":null,"strMusicVidScreen2":null,"strMusicVidScreen3":null,"intMusicVidViews":null,"intMusicVidLikes":null,"intMusicVidDislikes":null,"intMusicVidFavorites":null,"intMusicVidComments":null,"intTrackNumber":"11","intLoved":"0","intScore":null,"intScoreVotes":null,"intTotalListeners":null,"intTotalPlays":null,"strMusicBrainzID":"07810661-0473-4648-ac51-8d0fe52fa048","strMusicBrainzAlbumID":"0088f94b-d9f5-37a0-a7ce-499319c6e8ee","strMusicBrainzArtistID":"bd13909f-1c29-4c27-a874-d4aaf27c5b1a","strLocked":"unlocked"},{"idTrack":"32730366","idAlbum":"2110242","idArtist":"111280","idLyric":"176232","idIMVDB":null,"strTrack":"When It Comes to Love","strAlbum":"Behind the Mask","strArtist":"Fleetwood Mac","strArtistAlternate":null,"intCD":null,"intDuration":"248573","strGenre":"Rock","strMood":null,"strStyle":null,"strTheme":null,"strDescriptionEN":null,"strTrackThumb":null,"strTrack3DCase":null,"strTrackLyrics":null,"strMusicVid":null,"strMusicVidDirector":null,"strMusicVidCompany":null,"strMusicVidScreen1":null,"strMusicVidScreen2":null,"strMusicVidScreen3":null,"intMusicVidViews":null,"intMusicVidLikes":null,"intMusicVidDislikes":null,"intMusicVidFavorites":null,"intMusicVidComments":null,"intTrackNumber":"12","intLoved":"0","intScore":null,"intScoreVotes":null,"intTotalListeners":null,"intTotalPlays":null,"strMusicBrainzID":"36ba9e89-24bd-447b-ab67-372d8bfb8069","strMusicBrainzAlbumID":"0088f94b-d9f5-37a0-a7ce-499319c6e8ee","strMusicBrainzArtistID":"bd13909f-1c29-4c27-a874-d4aaf27c5b1a","strLocked":"unlocked"},{"idTrack":"32730367","idAlbum":"2110242","idArtist":"111280","idLyric":"176231","idIMVDB":null,"strTrack":"The Second Time","strAlbum":"Behind the Mask","strArtist":"Fleetwood Mac","strArtistAlternate":null,"intCD":null,"intDuration":"151893","strGenre":"Rock","strMood":null,"strStyle":null,"strTheme":null,"strDescriptionEN":null,"strTrackThumb":null,"strTrack3DCase":null,"strTrackLyrics":null,"strMusicVid":null,"strMusicVidDirector":null,"strMusicVidCompany":null,"strMusicVidScreen1":null,"strMusicVidScreen2":null,"strMusicVidScreen3":null,"intMusicVidViews":null,"intMusicVidLikes":null,"intMusicVidDislikes":null,"intMusicVidFavorites":null,"intMusicVidComments":null,"intTrackNumber":"13","intLoved":"0","intScore":null,"intScoreVotes":null,"intTotalListeners":null,"intTotalPlays":null,"strMusicBrainzID":"0d98bcc6-3dc1-463e-bad5-221d50e7227c","strMusicBrainzAlbumID":"0088f94b-d9f5-37a0-a7ce-499319c6e8ee","strMusicBrainzArtistID":"bd13909f-1c29-4c27-a874-d4aaf27c5b1a","strLocked":"unlocked"}]}